_piqtree.cpython-314-x86_64-linux-gnu.so
piqtree/__init__.py
piqtree/_data.py
piqtree/exceptions.py
piqtree/py.typed
piqtree/_app/__init__.py
piqtree/_libiqtree/_piqtree.cpp
piqtree/distribution/__init__.py
piqtree/distribution/indel_distribution.py
piqtree/iqtree/__init__.py
piqtree/iqtree/_alignment.py
piqtree/iqtree/_decorator.py
piqtree/iqtree/_jc_distance.py
piqtree/iqtree/_model_finder.py
piqtree/iqtree/_parse_tree_parameters.py
piqtree/iqtree/_random_tree.py
piqtree/iqtree/_robinson_foulds.py
piqtree/iqtree/_tree.py
piqtree/model/__init__.py
piqtree/model/_freq_type.py
piqtree/model/_model.py
piqtree/model/_options.py
piqtree/model/_rate_type.py
piqtree/model/_substitution_model.py
piqtree/util/__init__.py
piqtree.libs/libgomp-e985bcbb.so.1.0.0
piqtree-0.8.0.dist-info/METADATA
piqtree-0.8.0.dist-info/WHEEL
piqtree-0.8.0.dist-info/entry_points.txt
piqtree-0.8.0.dist-info/top_level.txt
piqtree-0.8.0.dist-info/RECORD
piqtree-0.8.0.dist-info/licenses/LICENSE
