Metadata-Version: 2.4
Name: piqtree
Version: 0.8.0
Summary: Python bindings for IQTree
Author: Gavin Huttley, Robert McArthur, Bui Quang Minh , Richard Morris, Thomas Wong
License-Expression: GPL-2.0-only
Project-URL: Repository, https://github.com/cogent3/piqtree
Project-URL: Documentation, https://piqtree.readthedocs.io
Classifier: Development Status :: 4 - Beta
Classifier: Intended Audience :: Science/Research
Classifier: Topic :: Scientific/Engineering :: Bio-Informatics
Classifier: Topic :: Software Development :: Libraries :: Python Modules
Classifier: Natural Language :: English
Classifier: Operating System :: Microsoft :: Windows
Classifier: Operating System :: MacOS
Classifier: Operating System :: POSIX :: Linux
Classifier: Programming Language :: C++
Classifier: Programming Language :: Python :: 3
Classifier: Programming Language :: Python :: 3.12
Classifier: Programming Language :: Python :: 3.13
Classifier: Programming Language :: Python :: 3.14
Classifier: Typing :: Typed
Requires-Python: >=3.12
License-File: LICENSE
Requires-Dist: cogent3>=2025.12.10a2
Requires-Dist: pyyaml
Requires-Dist: requests
Provides-Extra: dev
Requires-Dist: cibuildwheel==3.2.1; extra == "dev"
Requires-Dist: pybind11==3.0.1; extra == "dev"
Requires-Dist: delvewheel==1.11.2; extra == "dev"
Requires-Dist: scriv; extra == "dev"
Requires-Dist: piqtree[test]; extra == "dev"
Requires-Dist: piqtree[lint]; extra == "dev"
Requires-Dist: piqtree[typing]; extra == "dev"
Provides-Extra: test
Requires-Dist: pytest; extra == "test"
Requires-Dist: pytest-cov; extra == "test"
Requires-Dist: pytest-markdown-docs; extra == "test"
Requires-Dist: pytest-mock; extra == "test"
Requires-Dist: nox; extra == "test"
Provides-Extra: lint
Requires-Dist: ruff==0.14.8; extra == "lint"
Provides-Extra: typing
Requires-Dist: mypy==1.19.0; extra == "typing"
Requires-Dist: piqtree[stubs]; extra == "typing"
Requires-Dist: piqtree[test]; extra == "typing"
Provides-Extra: stubs
Requires-Dist: types-PyYAML; extra == "stubs"
Requires-Dist: types-requests; extra == "stubs"
Provides-Extra: extra
Requires-Dist: cogent3[extra]; extra == "extra"
Provides-Extra: doc
Requires-Dist: mkdocs; extra == "doc"
Requires-Dist: mkdocstrings[python]; extra == "doc"
Requires-Dist: mkdocs-jupyter; extra == "doc"
Requires-Dist: pymdown-extensions; extra == "doc"
Requires-Dist: jupytext; extra == "doc"
Requires-Dist: piqtree[test]; extra == "doc"
Requires-Dist: cogent3[extra]; extra == "doc"
Requires-Dist: diverse-seq>=2025.7.10; extra == "doc"
Requires-Dist: jupyter; extra == "doc"
Requires-Dist: ipywidgets; extra == "doc"
Dynamic: license-file
